{
  "success": true,
  "timestamp": "2025-08-31T21:49:28.312Z",
  "data": [
    {
      "address": "463vBSJt4CurDqEnojG3ykMy3Lf9GQF2hFV27JeZpump",
      "symbol": "HARLOD",
      "name": "HARLOD",
      "decimals": 6,
      "icon": "https://ipfs.io/ipfs/bafkreibbq7pla7rdmc4oialhgcfv4cn4fdjal4mgthpdtbtvctwdeyd7ii",
      "created_time": 1756531644,
      "website": "https://archive.4plebs.org/s4s/thread/1630863/#1630863",
      "twitter": "https://x.com/BigTrencher/status/1961661137855926580",
      "holder": 1156,
      "market_cap": 460327,
      "price": 0.0004603,
      "price_change_24h": 185,
      "volume_24h": 1691300.83,
      "pool_address": "solana_3YDNDoPtnLvd45ypQZcwxa4DeC1z26Yf6rC3gPe5b1ZN",
      "ath": 0.0006684,
      "ath_timestamp": 1756672512,
      "ath_pool": "3YDNDoPtnLvd45ypQZcwxa4DeC1z26Yf6rC3gPe5b1ZN",
      "dexId": "pumpswap",
      "pairAddress": "3YDNDoPtnLvd45ypQZcwxa4DeC1z26Yf6rC3gPe5b1ZN",
      "boosts": {
        "active": 50
      },
      "txns_24h": {
        "buys": 7150,
        "sells": 6396
      },
      "fdv_usd": 460327,
      "total_reserve_in_usd": 92090.06,
      "tags": [],
      "first_signal": {
        "timestamp": 1756670597,
        "price": 0.0006148
      },
      "metrics": {
        "uniqueWallets": 2,
        "inflow24h": 15239.831167765176,
        "trades": [
          {
            "timestamp": "2025-08-31T20:02:20.000Z",
            "type": "BUY",
            "amount": 14179555.849004,
            "usdValue": 7078.995512528146,
            "wallet": {
              "address": "8zFZHuSRuDpuAR7J6FzwyF3vKNx4CVW3DFHJerQhc7Zd",
              "name": "Pow"
            }
          },
          {
            "timestamp": "2025-08-31T05:56:56.000Z",
            "type": "BUY",
            "amount": 18206579.528035,
            "usdValue": 8160.83565523703,
            "wallet": {
              "address": "8deJ9xeUvXSJwicYptA9mHsU2rN2pDx37KWzkDkEXhU6",
              "name": "cooker"
            }
          }
        ]
      },
      "walletPortfolios": [
        {
          "address": "8zFZHuSRuDpuAR7J6FzwyF3vKNx4CVW3DFHJerQhc7Zd",
          "name": "Pow",
          "score": 3,
          "tokens": [
            {
              "token_address": "463vBSJt4CurDqEnojG3ykMy3Lf9GQF2hFV27JeZpump",
              "balance": 14179555.849004,
              "token_price": 0.0004603,
              "token_decimals": 6,
              "token_symbol": "HARLOD",
              "token_name": "HARLOD",
              "value": 6526.849557296542
            }
          ]
        },
        {
          "address": "8deJ9xeUvXSJwicYptA9mHsU2rN2pDx37KWzkDkEXhU6",
          "name": "cooker",
          "score": 2,
          "tokens": [
            {
              "token_address": "463vBSJt4CurDqEnojG3ykMy3Lf9GQF2hFV27JeZpump",
              "balance": 18206579.528035,
              "token_price": 0.0004603,
              "token_decimals": 6,
              "token_symbol": "HARLOD",
              "token_name": "HARLOD",
              "value": 8380.488556754512
            }
          ]
        }
      ]
    }
  ],
  "groups": {
    "latestSignals": [
      {
        "address": "463vBSJt4CurDqEnojG3ykMy3Lf9GQF2hFV27JeZpump",
        "symbol": "HARLOD",
        "name": "HARLOD",
        "decimals": 6,
        "icon": "https://ipfs.io/ipfs/bafkreibbq7pla7rdmc4oialhgcfv4cn4fdjal4mgthpdtbtvctwdeyd7ii",
        "created_time": 1756531644,
        "website": "https://archive.4plebs.org/s4s/thread/1630863/#1630863",
        "twitter": "https://x.com/BigTrencher/status/1961661137855926580",
        "holder": 1156,
        "market_cap": 460327,
        "price": 0.0004603,
        "price_change_24h": 185,
        "volume_24h": 1691300.83,
        "pool_address": "solana_3YDNDoPtnLvd45ypQZcwxa4DeC1z26Yf6rC3gPe5b1ZN",
        "ath": 0.0006684,
        "ath_timestamp": 1756672512,
        "ath_pool": "3YDNDoPtnLvd45ypQZcwxa4DeC1z26Yf6rC3gPe5b1ZN",
        "dexId": "pumpswap",
        "pairAddress": "3YDNDoPtnLvd45ypQZcwxa4DeC1z26Yf6rC3gPe5b1ZN",
        "boosts": {
          "active": 50
        },
        "txns_24h": {
          "buys": 7150,
          "sells": 6396
        },
        "fdv_usd": 460327,
        "total_reserve_in_usd": 92090.06,
        "tags": [],
        "first_signal": {
          "timestamp": 1756670597,
          "price": 0.0006148
        },
        "metrics": {
          "uniqueWallets": 2,
          "inflow24h": 15239.831167765176,
          "trades": [
            {
              "timestamp": "2025-08-31T20:02:20.000Z",
              "type": "BUY",
              "amount": 14179555.849004,
              "usdValue": 7078.995512528146,
              "wallet": {
                "address": "8zFZHuSRuDpuAR7J6FzwyF3vKNx4CVW3DFHJerQhc7Zd",
                "name": "Pow"
              }
            },
            {
              "timestamp": "2025-08-31T05:56:56.000Z",
              "type": "BUY",
              "amount": 18206579.528035,
              "usdValue": 8160.83565523703,
              "wallet": {
                "address": "8deJ9xeUvXSJwicYptA9mHsU2rN2pDx37KWzkDkEXhU6",
                "name": "cooker"
              }
            }
          ]
        },
        "walletPortfolios": [
          {
            "address": "8zFZHuSRuDpuAR7J6FzwyF3vKNx4CVW3DFHJerQhc7Zd",
            "name": "Pow",
            "score": 3,
            "tokens": [
              {
                "token_address": "463vBSJt4CurDqEnojG3ykMy3Lf9GQF2hFV27JeZpump",
                "balance": 14179555.849004,
                "token_price": 0.0004603,
                "token_decimals": 6,
                "token_symbol": "HARLOD",
                "token_name": "HARLOD",
                "value": 6526.849557296542
              }
            ]
          },
          {
            "address": "8deJ9xeUvXSJwicYptA9mHsU2rN2pDx37KWzkDkEXhU6",
            "name": "cooker",
            "score": 2,
            "tokens": [
              {
                "token_address": "463vBSJt4CurDqEnojG3ykMy3Lf9GQF2hFV27JeZpump",
                "balance": 18206579.528035,
                "token_price": 0.0004603,
                "token_decimals": 6,
                "token_symbol": "HARLOD",
                "token_name": "HARLOD",
                "value": 8380.488556754512
              }
            ]
          }
        ]
      }
    ],
    "buys": [],
    "sells": []
  }
}