{
  "success": true,
  "timestamp": "2025-08-28T13:34:18.378Z",
  "data": [
    {
      "address": "DMwbVy48dWVKGe9z1pcVnwF3HLMLrqWdDLfbvx8RchhK",
      "symbol": "Cope",
      "name": "Cope",
      "decimals": 6,
      "icon": "https://cf-ipfs.com/ipfs/QmbnQncuvvs7WZCCnGLnqFmMW9qbRzEUK8nKKprDuSeTf9",
      "created_time": 1712218394,
      "website": "",
      "twitter": "",
      "holder": 3344,
      "market_cap": 3897333,
      "price": 0.003999,
      "price_change_24h": 48.58,
      "volume_24h": 1067359.82,
      "pool_address": "solana_URqx24yyYxtXXhTbBQnbtPLhtLWYoaDaRxuQuLpNS3S",
      "ath": 0.00622439180913363,
      "ath_timestamp": 1756382400,
      "ath_pool": "URqx24yyYxtXXhTbBQnbtPLhtLWYoaDaRxuQuLpNS3S",
      "dexId": "meteora",
      "pairAddress": "4NDtQFcupnSuFUEsgKMnCCQkCcspH6uD9xfHcRSRrQ9Q",
      "txns_24h": {
        "buys": 2540,
        "sells": 2344
      },
      "fdv_usd": 3897333,
      "total_reserve_in_usd": 389965.63,
      "tags": [],
      "first_signal": {
        "timestamp": 1756382231,
        "price": 0.003991
      },
      "metrics": {
        "uniqueWallets": 3,
        "inflow24h": -60722.14064064742,
        "trades": [
          {
            "timestamp": "2025-08-28T11:56:14.000Z",
            "type": "BUY",
            "amount": 99389.211811,
            "usdValue": 399.039303145533,
            "wallet": {
              "address": "EJ2jyVUceCYvC1HxY77X2adre7Kcf8sQaucrKaQtVtXs",
              "name": "justice3.6x"
            }
          },
          {
            "timestamp": "2025-08-28T01:30:46.000Z",
            "type": "SELL",
            "amount": 1602537.295793,
            "usdValue": 4721.6526609872935,
            "wallet": {
              "address": "FTg1gqW7vPm4kdU1LPM7JJnizbgPdRDy2PitKw6mY27j",
              "name": "GriffWhale"
            }
          },
          {
            "timestamp": "2025-08-28T01:30:39.000Z",
            "type": "SELL",
            "amount": 1602537.295793,
            "usdValue": 4808.87291326036,
            "wallet": {
              "address": "FTg1gqW7vPm4kdU1LPM7JJnizbgPdRDy2PitKw6mY27j",
              "name": "GriffWhale"
            }
          },
          {
            "timestamp": "2025-08-28T01:30:33.000Z",
            "type": "SELL",
            "amount": 1335447.746493,
            "usdValue": 3888.3507487297047,
            "wallet": {
              "address": "FTg1gqW7vPm4kdU1LPM7JJnizbgPdRDy2PitKw6mY27j",
              "name": "GriffWhale"
            }
          },
          {
            "timestamp": "2025-08-28T01:30:33.000Z",
            "type": "SELL",
            "amount": 801268.647896,
            "usdValue": 2449.9294445888822,
            "wallet": {
              "address": "FTg1gqW7vPm4kdU1LPM7JJnizbgPdRDy2PitKw6mY27j",
              "name": "GriffWhale"
            }
          },
          {
            "timestamp": "2025-08-28T01:30:30.000Z",
            "type": "SELL",
            "amount": 1780596.995325,
            "usdValue": 5594.240532207742,
            "wallet": {
              "address": "FTg1gqW7vPm4kdU1LPM7JJnizbgPdRDy2PitKw6mY27j",
              "name": "GriffWhale"
            }
          },
          {
            "timestamp": "2025-08-28T01:30:25.000Z",
            "type": "SELL",
            "amount": 1780596.995325,
            "usdValue": 5574.649327489704,
            "wallet": {
              "address": "FTg1gqW7vPm4kdU1LPM7JJnizbgPdRDy2PitKw6mY27j",
              "name": "GriffWhale"
            }
          },
          {
            "timestamp": "2025-08-28T01:30:15.000Z",
            "type": "SELL",
            "amount": 1571114.995875,
            "usdValue": 4975.932732161587,
            "wallet": {
              "address": "FTg1gqW7vPm4kdU1LPM7JJnizbgPdRDy2PitKw6mY27j",
              "name": "GriffWhale"
            }
          },
          {
            "timestamp": "2025-08-28T01:29:27.000Z",
            "type": "SELL",
            "amount": 1848370.583382,
            "usdValue": 5517.599898470303,
            "wallet": {
              "address": "FTg1gqW7vPm4kdU1LPM7JJnizbgPdRDy2PitKw6mY27j",
              "name": "GriffWhale"
            }
          },
          {
            "timestamp": "2025-08-28T01:29:24.000Z",
            "type": "SELL",
            "amount": 1369163.395098,
            "usdValue": 4231.448388070487,
            "wallet": {
              "address": "FTg1gqW7vPm4kdU1LPM7JJnizbgPdRDy2PitKw6mY27j",
              "name": "GriffWhale"
            }
          },
          {
            "timestamp": "2025-08-28T01:29:20.000Z",
            "type": "SELL",
            "amount": 2416170.697231,
            "usdValue": 7837.759283501512,
            "wallet": {
              "address": "FTg1gqW7vPm4kdU1LPM7JJnizbgPdRDy2PitKw6mY27j",
              "name": "GriffWhale"
            }
          },
          {
            "timestamp": "2025-08-28T01:29:17.000Z",
            "type": "SELL",
            "amount": 2842553.761448,
            "usdValue": 9684.393143426254,
            "wallet": {
              "address": "FTg1gqW7vPm4kdU1LPM7JJnizbgPdRDy2PitKw6mY27j",
              "name": "GriffWhale"
            }
          },
          {
            "timestamp": "2025-08-28T00:32:28.000Z",
            "type": "SELL",
            "amount": 3367205.993571,
            "usdValue": 5200.344622924995,
            "wallet": {
              "address": "8deJ9xeUvXSJwicYptA9mHsU2rN2pDx37KWzkDkEXhU6",
              "name": "cooker"
            }
          },
          {
            "timestamp": "2025-08-27T20:51:24.000Z",
            "type": "BUY",
            "amount": 3367205.993571,
            "usdValue": 6199.072796748318,
            "wallet": {
              "address": "8deJ9xeUvXSJwicYptA9mHsU2rN2pDx37KWzkDkEXhU6",
              "name": "cooker"
            }
          },
          {
            "timestamp": "2025-08-27T19:18:39.000Z",
            "type": "SELL",
            "amount": 4964569.553071,
            "usdValue": 1144.735469469827,
            "wallet": {
              "address": "8deJ9xeUvXSJwicYptA9mHsU2rN2pDx37KWzkDkEXhU6",
              "name": "cooker"
            }
          },
          {
            "timestamp": "2025-08-27T19:18:38.000Z",
            "type": "SELL",
            "amount": 8936225.195526,
            "usdValue": 2199.572306082416,
            "wallet": {
              "address": "8deJ9xeUvXSJwicYptA9mHsU2rN2pDx37KWzkDkEXhU6",
              "name": "cooker"
            }
          },
          {
            "timestamp": "2025-08-27T19:18:38.000Z",
            "type": "SELL",
            "amount": 3971655.642455,
            "usdValue": 1031.1502450473479,
            "wallet": {
              "address": "8deJ9xeUvXSJwicYptA9mHsU2rN2pDx37KWzkDkEXhU6",
              "name": "cooker"
            }
          },
          {
            "timestamp": "2025-08-27T19:18:37.000Z",
            "type": "SELL",
            "amount": 1985827.821227,
            "usdValue": 542.0823468540833,
            "wallet": {
              "address": "8deJ9xeUvXSJwicYptA9mHsU2rN2pDx37KWzkDkEXhU6",
              "name": "cooker"
            }
          },
          {
            "timestamp": "2025-08-27T19:05:51.000Z",
            "type": "BUY",
            "amount": 8905458.6674,
            "usdValue": 1041.2306613656158,
            "wallet": {
              "address": "8deJ9xeUvXSJwicYptA9mHsU2rN2pDx37KWzkDkEXhU6",
              "name": "cooker"
            }
          },
          {
            "timestamp": "2025-08-27T19:05:48.000Z",
            "type": "BUY",
            "amount": 10952819.544879,
            "usdValue": 1041.2306613656158,
            "wallet": {
              "address": "8deJ9xeUvXSJwicYptA9mHsU2rN2pDx37KWzkDkEXhU6",
              "name": "cooker"
            }
          }
        ]
      },
      "walletPortfolios": [
        {
          "address": "EJ2jyVUceCYvC1HxY77X2adre7Kcf8sQaucrKaQtVtXs",
          "name": "justice3.6x",
          "score": 2,
          "tokens": [
            {
              "token_address": "DMwbVy48dWVKGe9z1pcVnwF3HLMLrqWdDLfbvx8RchhK",
              "balance": 99389.211811,
              "token_price": 0.003999,
              "token_decimals": 6,
              "token_symbol": "Cope",
              "token_name": "Cope",
              "value": 397.457458032189
            }
          ]
        },
        {
          "address": "FTg1gqW7vPm4kdU1LPM7JJnizbgPdRDy2PitKw6mY27j",
          "name": "GriffWhale",
          "score": 1,
          "tokens": [
            {
              "token_address": "DMwbVy48dWVKGe9z1pcVnwF3HLMLrqWdDLfbvx8RchhK",
              "balance": 0,
              "token_price": 0.003999,
              "token_decimals": 6,
              "token_symbol": "Cope",
              "token_name": "Cope",
              "value": 0
            }
          ]
        },
        {
          "address": "8deJ9xeUvXSJwicYptA9mHsU2rN2pDx37KWzkDkEXhU6",
          "name": "cooker",
          "score": 2,
          "tokens": [
            {
              "token_address": "DMwbVy48dWVKGe9z1pcVnwF3HLMLrqWdDLfbvx8RchhK",
              "balance": 0,
              "token_price": 0.003999,
              "token_decimals": 6,
              "token_symbol": "Cope",
              "token_name": "Cope",
              "value": 0
            }
          ]
        }
      ]
    }
  ],
  "groups": {
    "latestSignals": [
      {
        "address": "DMwbVy48dWVKGe9z1pcVnwF3HLMLrqWdDLfbvx8RchhK",
        "symbol": "Cope",
        "name": "Cope",
        "decimals": 6,
        "icon": "https://cf-ipfs.com/ipfs/QmbnQncuvvs7WZCCnGLnqFmMW9qbRzEUK8nKKprDuSeTf9",
        "created_time": 1712218394,
        "website": "",
        "twitter": "",
        "holder": 3344,
        "market_cap": 3897333,
        "price": 0.003999,
        "price_change_24h": 48.58,
        "volume_24h": 1067359.82,
        "pool_address": "solana_URqx24yyYxtXXhTbBQnbtPLhtLWYoaDaRxuQuLpNS3S",
        "ath": 0.00622439180913363,
        "ath_timestamp": 1756382400,
        "ath_pool": "URqx24yyYxtXXhTbBQnbtPLhtLWYoaDaRxuQuLpNS3S",
        "dexId": "meteora",
        "pairAddress": "4NDtQFcupnSuFUEsgKMnCCQkCcspH6uD9xfHcRSRrQ9Q",
        "txns_24h": {
          "buys": 2540,
          "sells": 2344
        },
        "fdv_usd": 3897333,
        "total_reserve_in_usd": 389965.63,
        "tags": [],
        "first_signal": {
          "timestamp": 1756382231,
          "price": 0.003991
        },
        "metrics": {
          "uniqueWallets": 3,
          "inflow24h": -60722.14064064742,
          "trades": [
            {
              "timestamp": "2025-08-28T11:56:14.000Z",
              "type": "BUY",
              "amount": 99389.211811,
              "usdValue": 399.039303145533,
              "wallet": {
                "address": "EJ2jyVUceCYvC1HxY77X2adre7Kcf8sQaucrKaQtVtXs",
                "name": "justice3.6x"
              }
            },
            {
              "timestamp": "2025-08-28T01:30:46.000Z",
              "type": "SELL",
              "amount": 1602537.295793,
              "usdValue": 4721.6526609872935,
              "wallet": {
                "address": "FTg1gqW7vPm4kdU1LPM7JJnizbgPdRDy2PitKw6mY27j",
                "name": "GriffWhale"
              }
            },
            {
              "timestamp": "2025-08-28T01:30:39.000Z",
              "type": "SELL",
              "amount": 1602537.295793,
              "usdValue": 4808.87291326036,
              "wallet": {
                "address": "FTg1gqW7vPm4kdU1LPM7JJnizbgPdRDy2PitKw6mY27j",
                "name": "GriffWhale"
              }
            },
            {
              "timestamp": "2025-08-28T01:30:33.000Z",
              "type": "SELL",
              "amount": 1335447.746493,
              "usdValue": 3888.3507487297047,
              "wallet": {
                "address": "FTg1gqW7vPm4kdU1LPM7JJnizbgPdRDy2PitKw6mY27j",
                "name": "GriffWhale"
              }
            },
            {
              "timestamp": "2025-08-28T01:30:33.000Z",
              "type": "SELL",
              "amount": 801268.647896,
              "usdValue": 2449.9294445888822,
              "wallet": {
                "address": "FTg1gqW7vPm4kdU1LPM7JJnizbgPdRDy2PitKw6mY27j",
                "name": "GriffWhale"
              }
            },
            {
              "timestamp": "2025-08-28T01:30:30.000Z",
              "type": "SELL",
              "amount": 1780596.995325,
              "usdValue": 5594.240532207742,
              "wallet": {
                "address": "FTg1gqW7vPm4kdU1LPM7JJnizbgPdRDy2PitKw6mY27j",
                "name": "GriffWhale"
              }
            },
            {
              "timestamp": "2025-08-28T01:30:25.000Z",
              "type": "SELL",
              "amount": 1780596.995325,
              "usdValue": 5574.649327489704,
              "wallet": {
                "address": "FTg1gqW7vPm4kdU1LPM7JJnizbgPdRDy2PitKw6mY27j",
                "name": "GriffWhale"
              }
            },
            {
              "timestamp": "2025-08-28T01:30:15.000Z",
              "type": "SELL",
              "amount": 1571114.995875,
              "usdValue": 4975.932732161587,
              "wallet": {
                "address": "FTg1gqW7vPm4kdU1LPM7JJnizbgPdRDy2PitKw6mY27j",
                "name": "GriffWhale"
              }
            },
            {
              "timestamp": "2025-08-28T01:29:27.000Z",
              "type": "SELL",
              "amount": 1848370.583382,
              "usdValue": 5517.599898470303,
              "wallet": {
                "address": "FTg1gqW7vPm4kdU1LPM7JJnizbgPdRDy2PitKw6mY27j",
                "name": "GriffWhale"
              }
            },
            {
              "timestamp": "2025-08-28T01:29:24.000Z",
              "type": "SELL",
              "amount": 1369163.395098,
              "usdValue": 4231.448388070487,
              "wallet": {
                "address": "FTg1gqW7vPm4kdU1LPM7JJnizbgPdRDy2PitKw6mY27j",
                "name": "GriffWhale"
              }
            },
            {
              "timestamp": "2025-08-28T01:29:20.000Z",
              "type": "SELL",
              "amount": 2416170.697231,
              "usdValue": 7837.759283501512,
              "wallet": {
                "address": "FTg1gqW7vPm4kdU1LPM7JJnizbgPdRDy2PitKw6mY27j",
                "name": "GriffWhale"
              }
            },
            {
              "timestamp": "2025-08-28T01:29:17.000Z",
              "type": "SELL",
              "amount": 2842553.761448,
              "usdValue": 9684.393143426254,
              "wallet": {
                "address": "FTg1gqW7vPm4kdU1LPM7JJnizbgPdRDy2PitKw6mY27j",
                "name": "GriffWhale"
              }
            },
            {
              "timestamp": "2025-08-28T00:32:28.000Z",
              "type": "SELL",
              "amount": 3367205.993571,
              "usdValue": 5200.344622924995,
              "wallet": {
                "address": "8deJ9xeUvXSJwicYptA9mHsU2rN2pDx37KWzkDkEXhU6",
                "name": "cooker"
              }
            },
            {
              "timestamp": "2025-08-27T20:51:24.000Z",
              "type": "BUY",
              "amount": 3367205.993571,
              "usdValue": 6199.072796748318,
              "wallet": {
                "address": "8deJ9xeUvXSJwicYptA9mHsU2rN2pDx37KWzkDkEXhU6",
                "name": "cooker"
              }
            },
            {
              "timestamp": "2025-08-27T19:18:39.000Z",
              "type": "SELL",
              "amount": 4964569.553071,
              "usdValue": 1144.735469469827,
              "wallet": {
                "address": "8deJ9xeUvXSJwicYptA9mHsU2rN2pDx37KWzkDkEXhU6",
                "name": "cooker"
              }
            },
            {
              "timestamp": "2025-08-27T19:18:38.000Z",
              "type": "SELL",
              "amount": 8936225.195526,
              "usdValue": 2199.572306082416,
              "wallet": {
                "address": "8deJ9xeUvXSJwicYptA9mHsU2rN2pDx37KWzkDkEXhU6",
                "name": "cooker"
              }
            },
            {
              "timestamp": "2025-08-27T19:18:38.000Z",
              "type": "SELL",
              "amount": 3971655.642455,
              "usdValue": 1031.1502450473479,
              "wallet": {
                "address": "8deJ9xeUvXSJwicYptA9mHsU2rN2pDx37KWzkDkEXhU6",
                "name": "cooker"
              }
            },
            {
              "timestamp": "2025-08-27T19:18:37.000Z",
              "type": "SELL",
              "amount": 1985827.821227,
              "usdValue": 542.0823468540833,
              "wallet": {
                "address": "8deJ9xeUvXSJwicYptA9mHsU2rN2pDx37KWzkDkEXhU6",
                "name": "cooker"
              }
            },
            {
              "timestamp": "2025-08-27T19:05:51.000Z",
              "type": "BUY",
              "amount": 8905458.6674,
              "usdValue": 1041.2306613656158,
              "wallet": {
                "address": "8deJ9xeUvXSJwicYptA9mHsU2rN2pDx37KWzkDkEXhU6",
                "name": "cooker"
              }
            },
            {
              "timestamp": "2025-08-27T19:05:48.000Z",
              "type": "BUY",
              "amount": 10952819.544879,
              "usdValue": 1041.2306613656158,
              "wallet": {
                "address": "8deJ9xeUvXSJwicYptA9mHsU2rN2pDx37KWzkDkEXhU6",
                "name": "cooker"
              }
            }
          ]
        },
        "walletPortfolios": [
          {
            "address": "EJ2jyVUceCYvC1HxY77X2adre7Kcf8sQaucrKaQtVtXs",
            "name": "justice3.6x",
            "score": 2,
            "tokens": [
              {
                "token_address": "DMwbVy48dWVKGe9z1pcVnwF3HLMLrqWdDLfbvx8RchhK",
                "balance": 99389.211811,
                "token_price": 0.003999,
                "token_decimals": 6,
                "token_symbol": "Cope",
                "token_name": "Cope",
                "value": 397.457458032189
              }
            ]
          },
          {
            "address": "FTg1gqW7vPm4kdU1LPM7JJnizbgPdRDy2PitKw6mY27j",
            "name": "GriffWhale",
            "score": 1,
            "tokens": [
              {
                "token_address": "DMwbVy48dWVKGe9z1pcVnwF3HLMLrqWdDLfbvx8RchhK",
                "balance": 0,
                "token_price": 0.003999,
                "token_decimals": 6,
                "token_symbol": "Cope",
                "token_name": "Cope",
                "value": 0
              }
            ]
          },
          {
            "address": "8deJ9xeUvXSJwicYptA9mHsU2rN2pDx37KWzkDkEXhU6",
            "name": "cooker",
            "score": 2,
            "tokens": [
              {
                "token_address": "DMwbVy48dWVKGe9z1pcVnwF3HLMLrqWdDLfbvx8RchhK",
                "balance": 0,
                "token_price": 0.003999,
                "token_decimals": 6,
                "token_symbol": "Cope",
                "token_name": "Cope",
                "value": 0
              }
            ]
          }
        ]
      }
    ],
    "buys": [],
    "sells": []
  }
}